{"LineeE005V-E005Z": ["padova autostazione", "padova piazzale boschetti", "padova ospedale", "padova pontecorvo via facciolati", "padova voltabarozzo", "roncaglia", "ponte san nicolo'", "legnaro", "vigorovea", "bv. brugine", "piove di sacco via marconi", "bv. tognana", "bv. cambroso", "codevigo ponte", "bv. san margherita d'a", "conche di codevigo", "valli chioggia", "chioggia fs", "chioggia c. marconi", "sottomarina ospedale", "sottomarina via zeno", "sottomarina hotel sole", "sottomarina bagni canarin", "sottomarina autostazione"], "LineaE045": ["padova autostazione", "padova stazione fs", "monta'", "ponterotto fornace", "taggi' di sotto", "taggi' di sopra", "villafranca padovana", "campodoro", "bevadoro", "torre rossa", "camisano", "bv smaria camisano", "grumolo delle abbadesse", "lerino", "torri di quartesolo centro", "vicenza stanga", "monteberico"], "LineeE066-E066Z": ["padova autostazione", "padova fiera", "padova stanga via venezia", "padova zi peroni", "padova zi cnr cso stati uniti", "padova zi via uruguay", "legnaro", "vigorovea", "bv brugine", "piove di sacco autostazione", "arzerello chiesa", "pontelongo", "villa del bosco", "correzzola", "concadalbero", "monsole civ 25/27", "pegolotte bar", "pegolotte centro", "cona", "rottanova"], "LineaE044": ["pilastro", "teonghio centro", "orgiano centro", "sossano", "colloredo", "campiglia", "ponticelli", "agugliaro", "lanzetta ponte", "lanzetta", "valbona", "lozzo chiesa", "lozzo via europa", "lozzo atestino", "chiavicone", "rivadolmo", "este"], "LineaE001_9": ["bagnoli di sopra", "anguillara", "borgoforte", "agna", "cona", "pegolotte centro", "cavarzere autostazione", "villa del bosco", "candiana", "bv correzzola", "pontelongo", "arzerello chiesa", "piove di sacco ospedale", "istituto de nicola"], "LineaE62_8": ["abano istituti", "abano giarre", "albignasego", "carpanedo", "masera'", "bv. cornegliana", "cornegliana", "bv. pontemanco", "due carrare san giorgio", "due carrare santo stefano", "cartura", "conselve", "bagnoli di sopra", "anguillara"], "LineaE101": ["san giorgio delle pertiche", "arsego", "busiago vecchio", "busiago nuovo", "marsango", "molini bivio", "tavo", "san maria di non", "biv marsango", "pieve interna", "campo san martino centro", "piazzola istituto"], "LineaE038_2": ["cittadella terminal", "cittadella girardi", "cittadella consorzio", "san giorgio in bosco", "villa del conte", "san giorgio delle pertiche", "busiago vecchio", "busiago nuovo", "marsango", "san maria di non", "tavo", "molini bivio", "arsego"], "LineeE009-E013V": ["padova autostazione", "padova piazzale boschetti", "padova ospedale", "padova pontecorvo via stoppato", "padova bassanello", "mandriola", "ponte fabbrica", "mezzavia", "battaglia via maggiore", "rivella", "monselice autostazione", "motta", "este", "este manfredini", "ospedaletto euganeo", "bv san margherita d'a", "megliadino san vitale", "casale di scodosia", "urbana", "merlara", "castelbaldo", "masi", "badia autostazione"], "LineaE002": ["padova autostazione", "padova piazzale boschetti", "padova ospedale", "padova pontecorvo via facciolati", "padova voltabarozzo", "roncaglia", "ponte san nicolo'", "legnaro", "vigorovea", "bv. brugine", "piove di sacco autostazione", "piove di sacco ospedale", "arzerello chiesa", "pontelongo", "bv. correzzola", "correzzola", "concadalbero", "monsole", "cantarana"], "LineaE098_3": ["noale autostaz actv", "san dono", "bv zeminiana", "massanzago", "bv massanzago", "massanzago via lovara", "massanzago via favariego", "straelle", "borgoricco banca sp10", "san michele b sp10", "bv smichele", "camposampiero istituto via puccini", "camposampiero"], "LineaE026": ["padova autostazione", "padova stazione fs", "padova giardini dell'arena", "padova corso garibaldi", "padova teatro verdi", "padova corso milano", "padova via vicenza", "padova brentelle", "rubano municipio", "mestrino", "bv. veggiano interna", "veggiano", "san antonio di veggiano", "san maria di veggiano", "montegalda", "montegaldella", "cervarese santa croce"], "LineaE004": ["padova autostazione", "padova piazzale boschetti", "padova ospedale", "padova pontecorvo via facciolati", "padova voltabarozzo", "roncaglia", "ponte san nicolo'", "legnaro", "vigorovea", "bv. brugine", "piove di sacco autostazione", "piove di sacco ospedale", "bv. arzerello", "arzergrande", "tognana chiesa", "vallonga", "codevigo", "brenta d'abba'", "treponti di correzzola", "cive'", "bv. sista", "ca' bianca"], "LineaE191": ["noale autostaz. actv", "trebaseleghe via treviso", "san ambrogio centro", "badoere sede bonaventura", "levada bar centrale", "torreselle via zanganili", "silvelle centro", "trebaseleghe don orione", "trebaseleghe ex cinema", "piombino dese centro", "piombino dese stadio", "piombino dese fiaschetteria", "loreggia via verdi", "fossalta", "rustega scuole elementari", "camposampiero paganini"], "LineaE035": ["agna", "frapiero", "candiana", "pontecasale", "arre al cristo", "arre", "arzercavalli", "terrassa padovana", "piove di sacco autostazione", "campagnola", "brugine", "brusadure chiesa", "bovolenta ponte", "polverara pizzeria", "bovolenta", "bv. ronchi", "ronchi centro", "casalserugo", "casalserugo ali'", "san giacomo", "padova via d'acquapendente", "padova istituto gramsci", "padova pontecorvo via stoppato", "padova ospedale", "padova piazzale boschetti", "padova autostazione"], "LineaE046": ["cologna veneta", "san sebastiano", "asigliano", "pezzelunghe", "pojana maggiore", "noventa vicentina", "capitello nov vic", "chiavicone", "valbona", "lozzo chiesa", "bv cinto da bomba", "caselle nov vic", "dossi chiesa", "ospedaletto euganeo", "este manfredini san 10", "este"], "LineaE042": ["este", "bv deserto", "san elena stazione fs", "san elena", "solesino via roma", "pisana", "bv cavarzerane"], "LineaE038": ["padova autostazione", "padova fs j avanzo", "padova stazione fs", "padova arcella", "vigodarzere", "saletto di vigodarzere", "tavo", "san maria di non", "molini", "cavino centro", "arsego", "marsango", "busiago nuovo", "busiago vecchio", "villa del conte", "san giorgio in bosco", "san anna morosina", "onara", "cittadella ospedale", "cittadella pta treviso", "cittadella consorzio"], "LineaE003": ["padova autostazione", "padova piazzale boschetti", "padova ospedale", "padova pontecorvo via facciolati", "padova voltabarozzo", "roncaglia", "ponte san nicolo'", "agripolis", "legnaro corte benedettina", "volparo asilo", "polverara", "bv. brusadure", "brugine via palu'", "brugine", "campagnola", "arzerello via cristo", "piove di sacco ospedale", "piove di sacco autostazione"], "LineaE007": ["padova autostazione", "padova piazzale boschetti", "padova ospedale", "padova pontecorvo via stoppato", "padova bassanello", "mandriola", "ponte fabbrica", "mezzavia", "battaglia via maggiore", "rivella", "monselice autostazione", "pernumia", "san pietro viminario", "vanzo", "tribano", "pozzonovo capolinea"], "LineaE071_6": ["bojon", "campolongo maggiore", "liettoli", "piove di sacco autostazione", "piovega", "san angelo di piove", "caovilla", "celeseo", "vigonovo", "saonara", "bv villatora", "padova istituto gramsci", "padova pontecorvo via facciolati", "padova via leopardi", "padova via manzoni", "padova prato della valle", "padova riv tito livio", "padova riv ponti romani", "padova giardini dell'arena", "padova stazione fs", "padova autostazione"], "LineaE035_2": ["due carrare santo stefano", "due carrare san giorgio", "masera'", "bertipaglia bivio", "da rizzato", "casalserugo", "polverara campo sportivo", "brusadure chiesa", "bovolenta", "campagnola", "arzerello via cristo", "piove di sacco ospedale", "piove istituti", "piove di sacco autostazione", "piove istituto de nicola", "terrassa municipio", "conselve"], "LineaE020": ["cervarese santa croce", "fossona municipio", "montemerlo ex cinema", "bresseo", "praglia", "san biagio", "feriole", "tencarola", "brusegana ospedale", "padova porta san giovanni", "padova corso milano", "padova teatro verdi", "padova corso garibaldi", "padova giardini dell'arena", "padova stazione fs", "padova autostazione"], "LineaE029": ["padova autostazione", "padova fs j. avanzo", "padova arcella", "vigodarzere", "saletto di vigodarzere", "tavo", "san maria di non", "molini", "cavino centro", "arsego", "san giorgio delle pertiche", "san giustina in colle", "tremarende", "villa del conte", "abbazia pisani", "san martino di lupari via puccini", "tombolo", "cittadella consorzio"], "LineaE073_1": ["stra", "noventana bar da marziano", "noventana chiesa", "noventa piazzale via valmarana sp33", "noventa piazzale bar rosso", "padova centro giotto", "padova stanga via venezia", "padova ospedale", "padova piazzale boschetti", "padova fiat", "padova fiera", "padova autostazione"], "LineaE034N": ["conselve", "san pietro viminario", "pernumia", "tribano", "pozzonovo centro", "monselice fs", "monselice autostazione", "ca' oddo", "schiavonia ospedale", "san elena trattoria", "deserto d'este", "este", "castelbaldo", "palugana", "bresega", "badia autostazione", "lendinara", "cinto euganeo", "lozzo atestino", "via '"], "LineaE041": ["padova autostazione", "padova fiera", "padova fiat", "padova stanga via venezia", "padova centro giotto", "ponte di brenta", "busa di vigonza", "peraga cacciane", "pionca", "codiverno", "bv. bussedo interna", "cognaro strada provinciale 88", "villanova", "bv. perotti", "mussolini", "borgoricco via gaffarello", "san eufemia", "san angelo di san maria di sala", "zeminiana chiesa", "borgoricco banca san .10"], "LineaE021_8": ["piazzola sul brenta", "campo san martino centro", "campo san martino bivio", "paviola", "san giorgio in bosco", "cittadella consorzio"], "LineaE047": ["badia autostazione", "masi", "castelbaldo", "merlara", "urbana", "casale scodosia ufficio postale", "montagnana istituto alberghiero", "montagnana viale fs", "montagnana pta legnago", "montagnana pta vicenza"], "LineaE033": ["anguillara", "agna", "san siro chiesa", "bagnoli di sopra", "olmo", "candiana", "pontecasale", "arre", "arzercavalli", "bovolenta", "terrassa padovana", "conselve", "tribano", "pozzonovo centro", "monselice autostazione", "bv. marendole", "motta", "este"], "LineaE060_Z-E060_V": ["padova autostazione", "padova fiera", "padova fiat", "padova stanga via venezia", "padova centro giotto", "ponte di brenta", "busa di vigonza", "perarolo", "vigonza", "mellaredo", "caselle dei ruffi", "san maria di sala", "treponti di san maria di sala", "stigliano", "bv. valli noale", "noale", "moniego", "scorze'", "scorze' drizzagno", "zero branco", "quinto di treviso", "treviso aeroporto", "treviso"], "LineaE098_4": ["reschigliano", "san andrea di campodarsego", "fiumicello", "borgoricco", "borgoricco banca sp10", "san michele b sp10", "bv smichele", "camposampiero istituto via puccini", "camposampiero"], "LineeEME015Z-E015V": ["turri capolinea", "montegrotto cataio 19", "montegrotto neroniana fr 2", "montegrotto viale stazione 115", "montegrotto viale stazione fr 44", "montegrotto municipio", "montegrotto corso terme piazza mercato", "montegrotto corso terme 92", "montegrotto corso terme fr 161", "abano configliachi fr 22", "abano volta 31", "abano ospedale", "abano via calle pace (hotel europa)", "abano viale terme 91", "abano matteotti fr municipio", "padova teatro verdi", "padova autostazione", "padova fiera", "padova fiat", "padova stanga via venezia", "padova centro giotto", "padova san lazzaro i^ strada", "padova allison i^ strada", "padova z.i. sede tim- via 7^ strada", "padova z.i. peroni", "padova z.i. via uruguay", "padova z.i. cnr corso stati uniti", "olmo quadrivio", "marghera autostrada", "marghera via rizzardi", "marghera agip", "venezia piazzale roma", "tessera aeroporto"], "LineaE192": ["camposampiero paganini", "san giustina distributore", "villa del conte bivio abbazzia", "villa del conte", "arsego", "bivio via cavinati", "san giorgio delle pertiche", "san giustina in colle"], "LineaE102": ["note mc", "cinto euganeo", "fontanafredda", "bv. fontanafredda", "lozzo atestino", "bv. valnogaredo", "bv. cortela'", "via '", "zovon", "teolo", "villa di teolo", "treponti di teolo", "cervarese santa croce", "fossona municipio", "montemerlo ex cinema", "bresseo", "praglia", "san biagio", "abano istituti"], "LineaE071": ["padova autostazione", "padova piazzale boschetti", "padova ospedale", "padova stanga via venezia", "padova centro giotto", "padova z.i. peroni", "camin centro", "bion valli", "tombelle", "vigonovo", "celeseo", "san angelo di piove", "piovega", "piove di sacco autostazione", "liettoli", "campolongo maggiore", "bojon", "campagna lupia", "lova"], "LineaE063": ["due carrare santo stefano", "due carrare san giorgio", "bv. pontemanco", "cornegliana", "bv. cornegliana int", "masera'", "bertipaglia", "masera' interna", "carpanedo", "albignasego", "padova guizza", "padova bassanello", "padova pontecorvo via stoppato", "padova ospedale", "padova piazzale boschetti", "padova autostazione"], "LineaE060_1": ["padova autostazione", "padova fiera", "padova fiat", "padova stanga via venezia", "padova centro giotto", "ponte di brenta", "busa di vigonza", "perarolo", "vigonza", "mellaredo", "murelle chiesa", "caselle dei ruffi interna"], "LineaE098_2": ["borgoricco banca sp10", "zeminiana chiesa", "san angelo di san maria di sala", "san eufemia", "borgoricco via gaffarello", "mussolini", "bv perotti", "villanova", "san andrea interna", "fiumicello", "bronzola", "san michele b sp10", "camposampiero istituto via puccini", "camposampiero"], "LineaE0316": ["padova autostazione", "padova stazione fs", "padova giardini dell'arena", "padova corso garibaldi", "padova teatro verdi", "padova corso milano", "padova via vicenza", "sarmeola c.c. le brentelle", "sarmeola viale piazzale", "rubano via borromeo imp.sport", "bosco di r. cimitero", "bosco di rubano interna", "rubano via toscana", "rubano viale europa", "rubano municipio", "rubano bv. via kennedy", "bosco di rubano", "rubano bv. via nespolaro", "villaguattera", "mestrino"], "LineaE018": ["padova autostazione", "padova stazione fs", "padova giardini dell'arena", "padova corso garibaldi", "padova teatro verdi", "padova corso milano", "padova porta san giovanni", "tencarola", "feriole", "san biagio", "praglia", "bresseo", "montemerlo ex cinema", "bv. treponti strada provinciale 20", "treponti di teolo", "teolo", "zovon", "via ' centro", "bv. cortela'", "bv. valnogaredo", "bv. fontanafredda", "fontanafredda", "cinto euganeo", "lozzo atestino", "valbona"], "LineaE034": ["agna", "anguillara", "san siro", "bagnoli", "olmo", "frapiero", "candiana", "pontecasale", "arre", "arzercavalli", "bovolenta", "terrassa padovana", "bertipaglia", "masera'", "bv. pontemanco", "due carrare san giorgio", "due carrare santo stefano", "cartura", "conselve", "tribano", "vanzo", "san pietro viminario", "pernumia", "battaglia via maggiore", "rivella", "monselice autostazione", "motta", "este"], "LineaE016": ["padova autostazione", "padova piazzale boschetti", "padova ospedale", "padova pontecorvo via stoppato", "padova bassanello", "mandriola", "ponte fabbrica", "mezzavia", "battaglia via maggiore", "rivella", "monselice autostazione", "san bortolo", "bv. cavarzerane", "solesino", "ponte gorzone", "stanghella zuccherificio", "boara pisani", "rovigo"], "LineaE019": ["barbarano", "ponte di barbarano", "lovolo", "ponte tezze", "via ' centro", "zovon esterna strada provinciale 38", "carbonara", "bv. rovolon", "rovolon", "bastia", "pozzetto", "cervarese santa croce", "fossona", "san martino della vanezza", "san marco trambacche", "saccolongo", "magnaboschi", "selvazzano centro", "tencarola", "padova porta san giovanni", "padova corso milano", "padova teatro verdi", "padova corso garibaldi", "padova giardini dell'arena", "padova stazione fs", "padova autostazione"], "LineaE043": ["este", "rivadolmo", "baone", "valle san giorgio", "cinto euganeo", "fontanafredda", "bv. fontanafredda", "lozzo atestino", "faedo", "valnogaredo centro", "bv. valnogaredo", "bv. cortela'", "via '", "zovon esterna strada provinciale 38", "carbonara", "bv. rovolon", "rovolon", "bastia", "pozzetto", "fossona municipio", "cervarese santa croce", "saccolongo"], "LineaE021": ["padova autostazione", "padova fs j. avanzo", "crowne plaza", "limena municipio", "vaccarino", "curtarolo", "pieve di curtarolo", "campo san martino centro", "campo san martino bivio", "paviola", "san giorgio bosco", "facca", "cittadella bv. fs", "cittadella porta treviso", "belvedere di tezze", "cusinati", "rosa'", "bassano stazione fs"], "LineaE073": ["padova autostazione", "padova piazzale boschetti", "padova ospedale", "padova istituto gramsci", "padova stanga via venezia", "padova centro giotto", "padova z.i. peroni", "noventa piazzale vill. san antonio", "noventa piazzale centro fitness", "noventa piazzale chiesa", "noventa piazzale municipio", "noventana chiesa", "noventana bar da marziano", "stra"], "LineaE103": ["abano istituti", "feriole", "selvazzano centro", "saccolongo", "fossona", "cervarese santa croce", "bastia", "carbonara", "zovon esterna san 38", "via '"], "LineeE010-E013V": ["padova autostazione", "padova piazzale boschetti", "padova ospedale", "padova pontecorvo via stoppato", "padova bassanello", "mandriola", "ponte fabbrica", "mezzavia", "battaglia via maggiore", "rivella", "monselice autostazione", "motta", "este", "vighizzolo", "deserto d'este", "villa estense", "carmignano d'este", "san urbano", "ca' morosini", "lendinara"], "LineeE011-E013V": ["padova autostazione", "padova piazzale boschetti", "padova ospedale", "padova pontecorvo via stoppato", "padova bassanello", "mandriola", "ponte fabbrica", "mezzavia", "battaglia via maggiore", "rivella", "monselice autostazione", "motta", "este", "este manfredini strada provinciale 91", "carceri", "vighizzolo"], "LineaE013_2": ["este", "este manfredini san 10", "ospedaletto euganeo", "san margherita d'adige", "megliadino san vitale", "casale di scodosia", "montagnana istituto alberghiero", "montagnana viale fs", "montagnana pta legnago", "montagnana pta vicenza"], "LineaE012-E013_V": ["cavazzana centro", "cavazzana trattoria", "lusia", "barbona municipio", "barbona chiesa", "vescovana chiesa", "granze", "san elena", "deserto d'este", "este", "motta", "monselice autostazione", "rivella", "battaglia vmaggiore", "mezzavia", "ponte fabbrica", "mandriola", "padova bassanello", "padova pontecorvo vstoppato", "padova ospedale", "padova piazzale boschetti", "padova autostazione"], "LineaE008-E013V": ["padova autostazione", "padova piazzale boschetti", "padova ospedale", "padova pontecorvo via stoppato", "padova bassanello", "mandriola", "ponte fabbrica", "mezzavia", "battaglia via maggiore", "rivella", "monselice autostazione", "motta", "este", "este manfredini strada provinciale 91", "palugana", "ponso", "bresega", "valli mocenighe", "piacenza d'adige", "masi", "badia autostazione"], "LineaE031": ["camisano", "torre rossa", "bevadoro", "campodoro interna", "lissaro", "mestrino", "rubano municipio", "padova brentelle", "padova via vicenza", "padova cso milano", "padova teatro verdi", "padova cso garibaldi", "padova giardini dell'arena", "padova stazione fs", "padova autostazione"], "LineaE017": ["padova autostazione", "padova stazione fs", "padova giardini dell'arena", "padova corso garibaldi", "padova teatro verdi", "padova corso milano", "padova porta san giovanni", "tencarola", "feriole", "san biagio", "praglia", "bresseo", "montemerlo ex cinema", "bv. treponti strada provinciale 20", "treponti di teolo", "teolo", "castelnuovo", "boccon centro", "zovon", "via ' centro", "via ' di sotto", "agugliaro", "ponte alto", "noventa vicentina"], "LineaE080": ["padova autostazione", "padova stazione fs", "padova giardini dell'arena", "padova corso garibaldi", "padova teatro verdi", "padova corso milano", "padova via vicenza", "padova brentelle", "rubano municipio", "mestrino", "arlesega", "grisignano di zocco hotel", "barbano", "bv. sarmego", "vancimuglio", "torri di quartesolo c.c. piramidi", "torri di quartesolo centro", "setteca' c. palladio", "vicenza stanga", "vicenza museo", "vicenza autostazione"], "LineaE074": ["padova autostazione", "padova fs j. avanzo", "limena municipio", "limena interna", "taggi' di sopra interna", "villafranca padovana", "bv. tremignon", "bv. villafranca", "vaccarino centro", "tremignon", "piazzola sul brenta", "presina", "isola due albere", "grantorto", "carmignano di brenta via ospitale", "carmignano di brenta", "cittadella porta treviso"], "LineaE006": ["padova autostazione", "padova piazzale boschetti", "padova ospedale", "padova pontecorvo vstoppato", "padova bassanello", "mandria chiesa", "abano stazione fs", "montegrotto terme", "torreglia", "galzignano", "valsanzibio", "arqua' parcheggio", "valle sgiorgio - bv arqua'", "baone", "monselice autostazione", "este"], "LineaE036": ["padova autostazione", "padova fs j. avanzo", "padova arcella", "castagnara", "reschigliano", "san andrea di campodarsego", "fiumicello", "bronzola tratt. scarin", "bronzola", "san michele delle badesse", "borgoricco banca san .10", "borgoricco", "straelle", "massanzago", "fossalta", "piombino dese", "trebaseleghe"], "LineaE024": ["mussolente municipio", "casoni", "marini", "cassola", "selle smarco", "rossano agip", "rossano", "rossano via san giustina", "mottinello", "galliera statue", "corte cittadella", "cittadella consorzio", "cittadella terminal"], "LineeE013Z-E013V": ["montagnana porta vicenza", "montagnana porta legnago", "montagnana viale fs", "montagnana istituto alberghiero", "montagnana porta padova", "montagnana san zeno", "megliadino san fidenzio", "saletto di montagnana", "ospedaletto euganeo", "este manfredini", "este", "motta", "monselice autostazione", "rivella", "battaglia via maggiore", "mezzavia", "ponte fabbrica", "mandriola", "padova bassanello", "padova pontecorvo via stoppato", "padova ospedale", "padova piazzale boschetti", "padova prato della valle", "padova riv tito livio", "padova riv ponti romani", "padova giardini dell'arena", "padova stazione fs", "padova autostazione"], "LineaE062": ["padova autostazione", "padova stazione fs", "padova giardini dell'arena", "padova riv ponti romani", "padova riv tito livio", "padova prato della valle", "padova piazzale boschetti", "padova ospedale", "padova pontecorvo via stoppato", "padova istituto gramsci", "padova bassanello", "padova guizza", "albignasego", "carpanedo", "masera' interna", "bertipaglia", "masera'", "cagnola", "cartura", "conselve", "olmo", "bagnoli municipio", "bagnoli di sopra", "san siro", "anguillara", "borgoforte", "agna"], "LineeE001-E604": ["padova autostazione", "padova piazzale boschetti", "padova ospedale", "padova pontecorvo via facciolati", "voltabarozzo", "roncaglia", "ponte san nicolo'", "legnaro", "vigorovea", "bv. brugine", "piove di sacco autostazione", "piove di sacco ospedale", "arzerello chiesa", "pontelongo", "bv. correzzola", "villa del bosco", "candiana", "correzzola", "concadalbero", "monsole civ. 25/27", "pegolotte bar", "cona", "rottanova", "agna", "cavarzere autostazione", "adria autostazione", "ariano ferrarese", "codigoro"], "LineaE040": ["padova autostazione", "padova stazione fs", "padova via giotto", "padova piazzale mazzini", "monta'", "ponterotto fornace", "taggi' di sotto", "taggi' di sopra", "villafranca padovana", "tremignon", "campodoro", "bevadoro", "torre rossa", "camisano", "piazzola sul brenta", "grossa", "bv. isola carturo", "gazzo", "barche", "san pietro in gu'"], "LineaE105": ["abano istituti", "tencarola", "caselle (liceo g galilei)", "sarmeola cc le brentelle", "rubano municipio", "mestrino", "lissaro", "campodoro", "villafranca bar", "piazzola sul brenta"], "LineaE076": ["padova autostazione", "padova piazzale boschetti", "padova ospedale", "padova pontecorvo via facciolati", "voltabarozzo", "roncaglia", "ponte san nicolo'", "legnaro", "vigorovea", "bv. brugine", "piove di sacco autostazione", "corte di piove di sacco", "rosara"], "LineaE046_1": ["rovigo", "boara pisani", "stanghella via d'acquisto", "san maria d'adige", "barbona chiesa", "vescovana chiesa", "granze", "bv granze", "finale", "villa estense interna", "deserto d'este", "este"], "LineaE037": ["padova autostazione", "padova fiera", "padova fiat", "padova stanga via venezia", "padova centro giotto", "ponte di brenta", "busa di vigonza", "peraga via giovanni xxiii", "vigonza via grandi", "vigonza chiesa", "barbariga", "pianiga", "caltana", "villa lanza", "bv. zianigo", "mirano ospedale"]}